{
    "4958.TW": {
        "name": "4958",
        "tactics": "⚡ 籌碼動能異常 (嚴禁追高，僅供波段觀察)",
        "trello_tip": "爆量 4.7 倍。此為市場雜訊觀測，請交由 NOC 核心執行長線濾網判定。"
    },
    "4919.TW": {
        "name": "4919",
        "tactics": "⚡ 籌碼動能異常 (嚴禁追高，僅供波段觀察)",
        "trello_tip": "爆量 12.1 倍。此為市場雜訊觀測，請交由 NOC 核心執行長線濾網判定。"
    },
    "9914.TW": {
        "name": "9914",
        "tactics": "⚡ 籌碼動能異常 (嚴禁追高，僅供波段觀察)",
        "trello_tip": "爆量 3.7 倍。此為市場雜訊觀測，請交由 NOC 核心執行長線濾網判定。"
    },
    "9921.TW": {
        "name": "9921",
        "tactics": "⚡ 籌碼動能異常 (嚴禁追高，僅供波段觀察)",
        "trello_tip": "爆量 2.5 倍。此為市場雜訊觀測，請交由 NOC 核心執行長線濾網判定。"
    }
}